autodistill_dinov2/__init__.py
autodistill_dinov2/dinov2_model.py
autodistill_dinov2-0.1.1.dist-info/LICENSE
autodistill_dinov2-0.1.1.dist-info/METADATA
autodistill_dinov2-0.1.1.dist-info/WHEEL
autodistill_dinov2-0.1.1.dist-info/top_level.txt
autodistill_dinov2-0.1.1.dist-info/RECORD
